mklibpy/__init__.py
mklibpy/error.py
mklibpy/json_config.py
mklibpy/code/__init__.py
mklibpy/code/func.py
mklibpy/data/__init__.py
mklibpy/data/column.py
mklibpy/data/config.py
mklibpy/data/list.py
mklibpy/data/obj.py
mklibpy/math/__init__.py
mklibpy/math/vector.py
mklibpy/math/vector2.py
mklibpy/math/vector3.py
mklibpy/terminal/__init__.py
mklibpy/terminal/colored_text.py
mklibpy/terminal/interact.py
mklibpy/util/__init__.py
mklibpy/util/args.py
mklibpy/util/list.py
mklibpy/util/osinfo.py
mklibpy/util/path.py
mklibpy/util/time.py
mklibpy-0.2.1.dist-info/DESCRIPTION.rst
mklibpy-0.2.1.dist-info/METADATA
mklibpy-0.2.1.dist-info/RECORD
mklibpy-0.2.1.dist-info/WHEEL
mklibpy-0.2.1.dist-info/metadata.json
mklibpy-0.2.1.dist-info/top_level.txt
